ose/__init__.py
ose/client.py
ose/exceptions.py
ose/resources/__init__.py
ose/resources/chats.py
ose/resources/deployments.py
ose/resources/sandboxes.py
ose/resources/usage.py
ose_cloud-1.0.1.dist-info/METADATA
ose_cloud-1.0.1.dist-info/WHEEL
ose_cloud-1.0.1.dist-info/top_level.txt
ose_cloud-1.0.1.dist-info/RECORD
